mongo_proxy/__init__.py
mongo_proxy/durable_cursor.py
mongo_proxy/mongodb_proxy.py
mongo_proxy/pymongo3_durable_cursor.py
MongoDBProxy_official-0.1.0.dist-info/LICENSE
MongoDBProxy_official-0.1.0.dist-info/METADATA
MongoDBProxy_official-0.1.0.dist-info/WHEEL
MongoDBProxy_official-0.1.0.dist-info/top_level.txt
MongoDBProxy_official-0.1.0.dist-info/RECORD
